{"t": "Executive Orders 2022 ", "p": "/us/md/exec/comar/01.01.2022", "et": "container", "dj": "/us/md/exec/comar/index.json", "fh": "/us/md/exec/comar/01.01.2022/index.full.html", "sc": "01.01.2022", "rp": "01|01|2022", "sp": "library|Code of Maryland Regulations|01|01|2022", "c": [{"t": "Executive Order 01.01.2022.01", "p": "/us/md/exec/comar/01.01.2022.01", "et": "section", "sc": "01.01.2022.01", "rp": "01|01|2022|.01", "sp": "library|Code of Maryland Regulations|01|01|2022|.01", "c": [{"t": "A.", "p": "/us/md/exec/comar/01.01.2022.01#A", "et": "para", "sc": "01.01.2022.01(A)", "rp": "01|01|2022|.01|A.", "x": "There is a Governor's Subcabinet on Infrastructure, a committee of the Gove"}, {"t": "B.", "p": "/us/md/exec/comar/01.01.2022.01#B", "et": "para", "sc": "01.01.2022.01(B)", "rp": "01|01|2022|.01|B.", "c": [{"t": "1.", "p": "/us/md/exec/comar/01.01.2022.01#B1", "et": "para", "sc": "01.01.2022.01(B)(1)", "rp": "01|01|2022|.01|B.|1.", "c": [{"t": "a.", "p": "/us/md/exec/comar/01.01.2022.01#B1a", "et": "para", "sc": "01.01.2022.01(B)(1)(a)", "rp": "01|01|2022|.01|B.|1.|a.", "x": "The Secretary of the Budget and Management;"}, {"t": "b.", "p": "/us/md/exec/comar/01.01.2022.01#B1b", "et": "para", "sc": "01.01.2022.01(B)(1)(b)", "rp": "01|01|2022|.01|B.|1.|b.", "x": "The Secretary of Transportation;"}, {"t": "c.", "p": "/us/md/exec/comar/01.01.2022.01#B1c", "et": "para", "sc": "01.01.2022.01(B)(1)(c)", "rp": "01|01|2022|.01|B.|1.|c.", "x": "The Secretary of Commerce;"}, {"t": "d.", "p": "/us/md/exec/comar/01.01.2022.01#B1d", "et": "para", "sc": "01.01.2022.01(B)(1)(d)", "rp": "01|01|2022|.01|B.|1.|d.", "x": "The Secretary of Housing and Community Development;"}, {"t": "e.", "p": "/us/md/exec/comar/01.01.2022.01#B1e", "et": "para", "sc": "01.01.2022.01(B)(1)(e)", "rp": "01|01|2022|.01|B.|1.|e.", "x": "The Secretary of the Environment; and"}, {"t": "f.", "p": "/us/md/exec/comar/01.01.2022.01#B1f", "et": "para", "sc": "01.01.2022.01(B)(1)(f)", "rp": "01|01|2022|.01|B.|1.|f.", "x": "The Secretary of Information Technology."}], "x": "The Subcabinet shall consist of:"}, {"t": "2.", "p": "/us/md/exec/comar/01.01.2022.01#B2", "et": "para", "sc": "01.01.2022.01(B)(2)", "rp": "01|01|2022|.01|B.|2.", "x": "The Director of the Maryland Energy Administration and the Executive Direct"}, {"t": "3.", "p": "/us/md/exec/comar/01.01.2022.01#B3", "et": "para", "sc": "01.01.2022.01(B)(3)", "rp": "01|01|2022|.01|B.|3.", "x": "The Governor shall designate a senior administrator in the Executive Branch"}, {"t": "4.", "p": "/us/md/exec/comar/01.01.2022.01#B4", "et": "para", "sc": "01.01.2022.01(B)(4)", "rp": "01|01|2022|.01|B.|4.", "x": "The Subcabinet shall make recommendations to the Governor on administering "}, {"t": "5.", "p": "/us/md/exec/comar/01.01.2022.01#B5", "et": "para", "sc": "01.01.2022.01(B)(5)", "rp": "01|01|2022|.01|B.|5.", "x": "Subcabinet members shall, as needed by the Governor or Chair, provide staff"}, {"t": "6.", "p": "/us/md/exec/comar/01.01.2022.01#B6", "et": "para", "sc": "01.01.2022.01(B)(6)", "rp": "01|01|2022|.01|B.|6.", "x": "The Governor or the Chair may establish subcommittees as needed to carry ou"}], "x": "Membership and Procedures."}]}, {"t": "Executive Order 01.01.2022.02", "p": "/us/md/exec/comar/01.01.2022.02", "et": "section", "sc": "01.01.2022.02", "rp": "01|01|2022|.02", "sp": "library|Code of Maryland Regulations|01|01|2022|.02", "c": [{"t": "A.", "p": "/us/md/exec/comar/01.01.2022.02#A", "et": "para", "sc": "01.01.2022.02(A)", "rp": "01|01|2022|.02|A.", "x": "There is a Maryland Behavioral Health and Public Safety Center of Excellenc"}, {"t": "B.", "p": "/us/md/exec/comar/01.01.2022.02#B", "et": "para", "sc": "01.01.2022.02(B)", "rp": "01|01|2022|.02|B.", "c": [{"t": "(1)", "p": "/us/md/exec/comar/01.01.2022.02#B(1)", "et": "para", "sc": "01.01.2022.02(B)(1)", "rp": "01|01|2022|.02|B.|(1)", "c": [{"t": "(a)", "p": "/us/md/exec/comar/01.01.2022.02#B(1)(a)", "et": "para", "sc": "01.01.2022.02(B)(1)(a)", "rp": "01|01|2022|.02|B.|(1)|(a)", "x": "The Lieutenant Governor, or the Lieutenant Governor\u2019s designee;"}, {"t": "(b)", "p": "/us/md/exec/comar/01.01.2022.02#B(1)(b)", "et": "para", "sc": "01.01.2022.02(B)(1)(b)", "rp": "01|01|2022|.02|B.|(1)|(b)", "x": "The Executive Director of the Governor\u2019s Office of Crime Prevention, Youth,"}, {"t": "(c)", "p": "/us/md/exec/comar/01.01.2022.02#B(1)(c)", "et": "para", "sc": "01.01.2022.02(B)(1)(c)", "rp": "01|01|2022|.02|B.|(1)|(c)", "x": "The Secretary of Health, or the Secretary\u2019s designee; and"}, {"t": "(d)", "p": "/us/md/exec/comar/01.01.2022.02#B(1)(d)", "et": "para", "sc": "01.01.2022.02(B)(1)(d)", "rp": "01|01|2022|.02|B.|(1)|(d)", "x": "The Secretary of Public Safety and Correctional Services, or the Secretary\u2019"}], "x": "The Group shall consist of the following members:"}, {"t": "(2)", "p": "/us/md/exec/comar/01.01.2022.02#B(2)", "et": "para", "sc": "01.01.2022.02(B)(2)", "rp": "01|01|2022|.02|B.|(2)", "c": [{"t": "(a)", "p": "/us/md/exec/comar/01.01.2022.02#B(2)(a)", "et": "para", "sc": "01.01.2022.02(B)(2)(a)", "rp": "01|01|2022|.02|B.|(2)|(a)", "x": "A designee of the President of the Senate;"}, {"t": "(b)", "p": "/us/md/exec/comar/01.01.2022.02#B(2)(b)", "et": "para", "sc": "01.01.2022.02(B)(2)(b)", "rp": "01|01|2022|.02|B.|(2)|(b)", "x": "A designee of the Speaker of the House of Delegates;"}, {"t": "(c)", "p": "/us/md/exec/comar/01.01.2022.02#B(2)(c)", "et": "para", "sc": "01.01.2022.02(B)(2)(c)", "rp": "01|01|2022|.02|B.|(2)|(c)", "x": "A representative of the Maryland Chiefs of Police Association;"}, {"t": "(d)", "p": "/us/md/exec/comar/01.01.2022.02#B(2)(d)", "et": "para", "sc": "01.01.2022.02(B)(2)(d)", "rp": "01|01|2022|.02|B.|(2)|(d)", "x": "A representative of the Maryland Sheriffs\u2019 Association;"}, {"t": "(e)", "p": "/us/md/exec/comar/01.01.2022.02#B(2)(e)", "et": "para", "sc": "01.01.2022.02(B)(2)(e)", "rp": "01|01|2022|.02|B.|(2)|(e)", "x": "A representative of the Mental Health Association of Maryland;"}, {"t": "(f)", "p": "/us/md/exec/comar/01.01.2022.02#B(2)(f)", "et": "para", "sc": "01.01.2022.02(B)(2)(f)", "rp": "01|01|2022|.02|B.|(2)|(f)", "x": "A representative of the National Alliance on Mental Illness of Maryland; an"}, {"t": "(g)", "p": "/us/md/exec/comar/01.01.2022.02#B(2)(g)", "et": "para", "sc": "01.01.2022.02(B)(2)(g)", "rp": "01|01|2022|.02|B.|(2)|(g)", "x": "A representative of the Substance Abuse and Mental Health Services Administ"}], "x": "The following shall, upon acceptance of membership, be additional Group mem"}, {"t": "(3)", "p": "/us/md/exec/comar/01.01.2022.02#B(3)", "et": "para", "sc": "01.01.2022.02(B)(3)", "rp": "01|01|2022|.02|B.|(3)", "x": "The Governor\u2019s Office of Crime Prevention, Youth, and Victim Services shall"}], "x": "Membership"}, {"t": "C.", "p": "/us/md/exec/comar/01.01.2022.02#C", "et": "para", "sc": "01.01.2022.02(C)", "rp": "01|01|2022|.02|C.", "c": [{"t": "(1)", "p": "/us/md/exec/comar/01.01.2022.02#C(1)", "et": "para", "sc": "01.01.2022.02(C)(1)", "rp": "01|01|2022|.02|C.|(1)", "x": "The Lieutenant Governor or the Lieutenant Governor\u2019s designee shall be Chai"}, {"t": "(2)", "p": "/us/md/exec/comar/01.01.2022.02#C(2)", "et": "para", "sc": "01.01.2022.02(C)(2)", "rp": "01|01|2022|.02|C.|(2)", "c": [{"t": "(a)", "p": "/us/md/exec/comar/01.01.2022.02#C(2)(a)", "et": "para", "sc": "01.01.2022.02(C)(2)(a)", "rp": "01|01|2022|.02|C.|(2)|(a)", "x": "Oversee the work of the Group;"}, {"t": "(b)", "p": "/us/md/exec/comar/01.01.2022.02#C(2)(b)", "et": "para", "sc": "01.01.2022.02(C)(2)(b)", "rp": "01|01|2022|.02|C.|(2)|(b)", "x": "Determine the Group\u2019s agenda; and"}, {"t": "(c)", "p": "/us/md/exec/comar/01.01.2022.02#C(2)(c)", "et": "para", "sc": "01.01.2022.02(C)(2)(c)", "rp": "01|01|2022|.02|C.|(2)|(c)", "x": "Identify additional support needs of the Group."}], "x": "The Chair shall:"}, {"t": "(3)", "p": "/us/md/exec/comar/01.01.2022.02#C(3)", "et": "para", "sc": "01.01.2022.02(C)(3)", "rp": "01|01|2022|.02|C.|(3)", "x": "The Group shall convene as frequently as necessary to satisfy its responsib"}, {"t": "(4)", "p": "/us/md/exec/comar/01.01.2022.02#C(4)", "et": "para", "sc": "01.01.2022.02(C)(4)", "rp": "01|01|2022|.02|C.|(4)", "x": "A majority of the Group\u2019s members is a quorum for the transaction of Group "}, {"t": "(5)", "p": "/us/md/exec/comar/01.01.2022.02#C(5)", "et": "para", "sc": "01.01.2022.02(C)(5)", "rp": "01|01|2022|.02|C.|(5)", "x": "The Group may adopt other procedures as necessary to ensure the orderly tra"}], "x": "Procedures"}, {"t": "D.", "p": "/us/md/exec/comar/01.01.2022.02#D", "et": "para", "sc": "01.01.2022.02(D)", "rp": "01|01|2022|.02|D.", "c": [{"t": "(1)", "p": "/us/md/exec/comar/01.01.2022.02#D(1)", "et": "para", "sc": "01.01.2022.02(D)(1)", "rp": "01|01|2022|.02|D.|(1)", "x": "Advise on the development and implementation of the Maryland Behavioral Hea"}, {"t": "(2)", "p": "/us/md/exec/comar/01.01.2022.02#D(2)", "et": "para", "sc": "01.01.2022.02(D)(2)", "rp": "01|01|2022|.02|D.|(2)", "x": "Support the Center of Excellence\u2019s Sequential Intercept Model as a planning"}, {"t": "(3)", "p": "/us/md/exec/comar/01.01.2022.02#D(3)", "et": "para", "sc": "01.01.2022.02(D)(3)", "rp": "01|01|2022|.02|D.|(3)", "x": "Locate potential federal funding streams that the Center of Excellence can "}, {"t": "(4)", "p": "/us/md/exec/comar/01.01.2022.02#D(4)", "et": "para", "sc": "01.01.2022.02(D)(4)", "rp": "01|01|2022|.02|D.|(4)", "x": "Assist in the creation of repositories of best practices throughout the sta"}, {"t": "(5)", "p": "/us/md/exec/comar/01.01.2022.02#D(5)", "et": "para", "sc": "01.01.2022.02(D)(5)", "rp": "01|01|2022|.02|D.|(5)", "x": "Perform other appropriate duties or responsibilities as recommended by the "}], "x": "The Group shall:"}]}, {"t": "Executive Order 01.01.2022.03", "p": "/us/md/exec/comar/01.01.2022.03", "et": "section", "sc": "01.01.2022.03", "rp": "01|01|2022|.03", "sp": "library|Code of Maryland Regulations|01|01|2022|.03", "c": [{"t": "A.", "p": "/us/md/exec/comar/01.01.2022.03#A", "et": "para", "sc": "01.01.2022.03(A)", "rp": "01|01|2022|.03|A.", "c": [{"t": "1.", "p": "/us/md/exec/comar/01.01.2022.03#A1", "et": "para", "sc": "01.01.2022.03(A)(1)", "rp": "01|01|2022|.03|A.|1.", "c": [{"t": "i.", "p": "/us/md/exec/comar/01.01.2022.03#A1i", "et": "para", "sc": "01.01.2022.03(A)(1)(i)", "rp": "01|01|2022|.03|A.|1.|i.", "x": "The Platform; and"}, {"t": "ii.", "p": "/us/md/exec/comar/01.01.2022.03#A1ii", "et": "para", "sc": "01.01.2022.03(A)(1)(ii)", "rp": "01|01|2022|.03|A.|1.|ii.", "x": "Business products, applications, data, and services in the Portfolio, as ma"}], "x": "\u201cOperator\u201d means the unit of State government designated by the MD THINK Co"}, {"t": "2.", "p": "/us/md/exec/comar/01.01.2022.03#A2", "et": "para", "sc": "01.01.2022.03(A)(2)", "rp": "01|01|2022|.03|A.|2.", "c": [{"t": "i.", "p": "/us/md/exec/comar/01.01.2022.03#A2i", "et": "para", "sc": "01.01.2022.03(A)(2)(i)", "rp": "01|01|2022|.03|A.|2.|i.", "x": "Operates business products, applications, data, or services on the Platform"}, {"t": "ii.", "p": "/us/md/exec/comar/01.01.2022.03#A2ii", "et": "para", "sc": "01.01.2022.03(A)(2)(ii)", "rp": "01|01|2022|.03|A.|2.|ii.", "x": "Contributes funding to support the development, operation, and maintenance "}, {"t": "iii.", "p": "/us/md/exec/comar/01.01.2022.03#A2iii", "et": "para", "sc": "01.01.2022.03(A)(2)(iii)", "rp": "01|01|2022|.03|A.|2.|iii.", "x": "Executes an agreement for access to, or operation or use of, the business p"}], "x": "\u201cParticipating Unit\u201d means a unit of State government approved by the MD TH"}, {"t": "3.", "p": "/us/md/exec/comar/01.01.2022.03#A3", "et": "para", "sc": "01.01.2022.03(A)(3)", "rp": "01|01|2022|.03|A.|3.", "x": "\u201cPlatform\u201d means the MD THINK platform composed of the servers, network inf"}, {"t": "4.", "p": "/us/md/exec/comar/01.01.2022.03#A4", "et": "para", "sc": "01.01.2022.03(A)(4)", "rp": "01|01|2022|.03|A.|4.", "x": "\u201cPortfolio\u201d means the business products, applications, data, and services h"}, {"t": "5.", "p": "/us/md/exec/comar/01.01.2022.03#A5", "et": "para", "sc": "01.01.2022.03(A)(5)", "rp": "01|01|2022|.03|A.|5.", "x": "\u201cStrategic Initiatives Office\u201d means a management office to support the MD "}, {"t": "6.", "p": "/us/md/exec/comar/01.01.2022.03#A6", "et": "para", "sc": "01.01.2022.03(A)(6)", "rp": "01|01|2022|.03|A.|6.", "x": "\u201cMD THINK Enterprise\u201d means the combination authorized resources or provide"}], "x": "The following terms have the meanings indicated:"}, {"t": "B.", "p": "/us/md/exec/comar/01.01.2022.03#B", "et": "para", "sc": "01.01.2022.03(B)", "rp": "01|01|2022|.03|B.", "c": [{"t": "1.", "p": "/us/md/exec/comar/01.01.2022.03#B1", "et": "para", "sc": "01.01.2022.03(B)(1)", "rp": "01|01|2022|.03|B.|1.", "x": "There is a MD THINK Committee of the Governor\u2019s Executive Council."}, {"t": "2.", "p": "/us/md/exec/comar/01.01.2022.03#B2", "et": "para", "sc": "01.01.2022.03(B)(2)", "rp": "01|01|2022|.03|B.|2.", "c": [{"t": "i.", "p": "/us/md/exec/comar/01.01.2022.03#B2i", "et": "para", "sc": "01.01.2022.03(B)(2)(i)", "rp": "01|01|2022|.03|B.|2.|i.", "x": "The Secretary of Budget and Management;"}, {"t": "ii.", "p": "/us/md/exec/comar/01.01.2022.03#B2ii", "et": "para", "sc": "01.01.2022.03(B)(2)(ii)", "rp": "01|01|2022|.03|B.|2.|ii.", "x": "The Secretary of Human Services;"}, {"t": "iii.", "p": "/us/md/exec/comar/01.01.2022.03#B2iii", "et": "para", "sc": "01.01.2022.03(B)(2)(iii)", "rp": "01|01|2022|.03|B.|2.|iii.", "x": "The Secretary of Information Technology;"}, {"t": "iv.", "p": "/us/md/exec/comar/01.01.2022.03#B2iv", "et": "para", "sc": "01.01.2022.03(B)(2)(iv)", "rp": "01|01|2022|.03|B.|2.|iv.", "x": "The Secretary of Juvenile Services;"}, {"t": "v.", "p": "/us/md/exec/comar/01.01.2022.03#B2v", "et": "para", "sc": "01.01.2022.03(B)(2)(v)", "rp": "01|01|2022|.03|B.|2.|v.", "x": "The Secretary of Health; and"}, {"t": "vi.", "p": "/us/md/exec/comar/01.01.2022.03#B2vi", "et": "para", "sc": "01.01.2022.03(B)(2)(vi)", "rp": "01|01|2022|.03|B.|2.|vi.", "x": "The Secretary of Public Safety and Correctional Services."}], "x": "The members of the MD THINK Committee shall be:"}, {"t": "3.", "p": "/us/md/exec/comar/01.01.2022.03#B3", "et": "para", "sc": "01.01.2022.03(B)(3)", "rp": "01|01|2022|.03|B.|3.", "x": "The Governor or his designee shall chair the MD THINK Committee."}, {"t": "4.", "p": "/us/md/exec/comar/01.01.2022.03#B4", "et": "para", "sc": "01.01.2022.03(B)(4)", "rp": "01|01|2022|.03|B.|4.", "c": [{"t": "i.", "p": "/us/md/exec/comar/01.01.2022.03#B4i", "et": "para", "sc": "01.01.2022.03(B)(4)(i)", "rp": "01|01|2022|.03|B.|4.|i.", "x": "Promote the appropriate sharing of data among units of State government;"}, {"t": "ii.", "p": "/us/md/exec/comar/01.01.2022.03#B4ii", "et": "para", "sc": "01.01.2022.03(B)(4)(ii)", "rp": "01|01|2022|.03|B.|4.|ii.", "x": "Set policy, objectives, and priorities for, and govern, the portfolio data,"}, {"t": "iii.", "p": "/us/md/exec/comar/01.01.2022.03#B4iii", "et": "para", "sc": "01.01.2022.03(B)(4)(iii)", "rp": "01|01|2022|.03|B.|4.|iii.", "x": "Be responsible for the protection, privacy, and appropriate use of shared d"}, {"t": "iv.", "p": "/us/md/exec/comar/01.01.2022.03#B4iv", "et": "para", "sc": "01.01.2022.03(B)(4)(iv)", "rp": "01|01|2022|.03|B.|4.|iv.", "x": "Designate the Operator;"}, {"t": "v.", "p": "/us/md/exec/comar/01.01.2022.03#B4v", "et": "para", "sc": "01.01.2022.03(B)(4)(v)", "rp": "01|01|2022|.03|B.|4.|v.", "x": "Oversee, coordinate, and authorize the assignment or provision of resources"}, {"t": "vi.", "p": "/us/md/exec/comar/01.01.2022.03#B4vi", "et": "para", "sc": "01.01.2022.03(B)(4)(vi)", "rp": "01|01|2022|.03|B.|4.|vi.", "x": "Establish working groups;"}, {"t": "vii.", "p": "/us/md/exec/comar/01.01.2022.03#B4vii", "et": "para", "sc": "01.01.2022.03(B)(4)(vii)", "rp": "01|01|2022|.03|B.|4.|vii.", "x": "Support the Two Generation Family Economic Security Commission in transform"}, {"t": "viii.", "p": "/us/md/exec/comar/01.01.2022.03#B4viii", "et": "para", "sc": "01.01.2022.03(B)(4)(viii)", "rp": "01|01|2022|.03|B.|4.|viii.", "x": "Make recommendations for State policies and the delivery of services to tho"}, {"t": "ix.", "p": "/us/md/exec/comar/01.01.2022.03#B4ix", "et": "para", "sc": "01.01.2022.03(B)(4)(ix)", "rp": "01|01|2022|.03|B.|4.|ix.", "c": [{"t": "1)", "p": "/us/md/exec/comar/01.01.2022.03#B4ix1)", "et": "para", "sc": "01.01.2022.03(B)(4)(ix)(1)", "rp": "01|01|2022|.03|B.|4.|ix.|1)", "x": "Its activities and plans in regard to data sharing in the State;"}, {"t": "2)", "p": "/us/md/exec/comar/01.01.2022.03#B4ix2)", "et": "para", "sc": "01.01.2022.03(B)(4)(ix)(2)", "rp": "01|01|2022|.03|B.|4.|ix.|2)", "x": "The impact of its work on Maryland citizens; and"}, {"t": "3)", "p": "/us/md/exec/comar/01.01.2022.03#B4ix3)", "et": "para", "sc": "01.01.2022.03(B)(4)(ix)(3)", "rp": "01|01|2022|.03|B.|4.|ix.|3)", "x": "Recommendations for future Executive Branch actions to support increased co"}], "x": "Produce a report to the Governor, on or before December 15 of each year, ad"}], "x": "The MD THINK Committee shall:"}], "x": "MD THINK Committee"}, {"t": "C.", "p": "/us/md/exec/comar/01.01.2022.03#C", "et": "para", "sc": "01.01.2022.03(C)", "rp": "01|01|2022|.03|C.", "c": [{"t": "1.", "p": "/us/md/exec/comar/01.01.2022.03#C1", "et": "para", "sc": "01.01.2022.03(C)(1)", "rp": "01|01|2022|.03|C.|1.", "x": "There is an MD THINK Executive Director."}, {"t": "2.", "p": "/us/md/exec/comar/01.01.2022.03#C2", "et": "para", "sc": "01.01.2022.03(C)(2)", "rp": "01|01|2022|.03|C.|2.", "x": "The MD THINK Executive Director shall be designated by and serve at the ple"}, {"t": "3.", "p": "/us/md/exec/comar/01.01.2022.03#C3", "et": "para", "sc": "01.01.2022.03(C)(3)", "rp": "01|01|2022|.03|C.|3.", "x": "The MD THINK Executive Director shall be, as directed by the Governor, part"}, {"t": "4.", "p": "/us/md/exec/comar/01.01.2022.03#C4", "et": "para", "sc": "01.01.2022.03(C)(4)", "rp": "01|01|2022|.03|C.|4.", "c": [{"t": "i.", "p": "/us/md/exec/comar/01.01.2022.03#C4i", "et": "para", "sc": "01.01.2022.03(C)(4)(i)", "rp": "01|01|2022|.03|C.|4.|i.", "x": "Use and manage the MD THINK Enterprise to achieve MD THINK Committee goals "}, {"t": "ii.", "p": "/us/md/exec/comar/01.01.2022.03#C4ii", "et": "para", "sc": "01.01.2022.03(C)(4)(ii)", "rp": "01|01|2022|.03|C.|4.|ii.", "x": "Facilitate and coordinate the delivery of portfolio products and services; "}, {"t": "iii.", "p": "/us/md/exec/comar/01.01.2022.03#C4iii", "et": "para", "sc": "01.01.2022.03(C)(4)(iii)", "rp": "01|01|2022|.03|C.|4.|iii.", "x": "Ensure the faithful execution of all agreements entered into by the operato"}], "x": "The MD THINK Executive Director shall:"}], "x": "MD THINK Executive Director."}, {"t": "D.", "p": "/us/md/exec/comar/01.01.2022.03#D", "et": "para", "sc": "01.01.2022.03(D)", "rp": "01|01|2022|.03|D.", "c": [{"t": "1.", "p": "/us/md/exec/comar/01.01.2022.03#D1", "et": "para", "sc": "01.01.2022.03(D)(1)", "rp": "01|01|2022|.03|D.|1.", "x": "Provide support to Participating Units, in accordance with the policies, ob"}, {"t": "2.", "p": "/us/md/exec/comar/01.01.2022.03#D2", "et": "para", "sc": "01.01.2022.03(D)(2)", "rp": "01|01|2022|.03|D.|2.", "x": "Conform to modernized and current business and technological standards; and"}, {"t": "3.", "p": "/us/md/exec/comar/01.01.2022.03#D3", "et": "para", "sc": "01.01.2022.03(D)(3)", "rp": "01|01|2022|.03|D.|3.", "x": "Host and manage modernized applications and shared data for the Medicaid Mo"}], "x": "The Platform shall be developed, maintained, and operated to:"}, {"t": "E.", "p": "/us/md/exec/comar/01.01.2022.03#E", "et": "para", "sc": "01.01.2022.03(E)", "rp": "01|01|2022|.03|E.", "c": [{"t": "1.", "p": "/us/md/exec/comar/01.01.2022.03#E1", "et": "para", "sc": "01.01.2022.03(E)(1)", "rp": "01|01|2022|.03|E.|1.", "x": "Coordinate and manage the work and activities of the MD THINK Committee;"}, {"t": "2.", "p": "/us/md/exec/comar/01.01.2022.03#E2", "et": "para", "sc": "01.01.2022.03(E)(2)", "rp": "01|01|2022|.03|E.|2.", "x": "Assess the Platform and Portfolio\u2019s compliance with the policies, objective"}, {"t": "3.", "p": "/us/md/exec/comar/01.01.2022.03#E3", "et": "para", "sc": "01.01.2022.03(E)(3)", "rp": "01|01|2022|.03|E.|3.", "c": [{"t": "i.", "p": "/us/md/exec/comar/01.01.2022.03#E3i", "et": "para", "sc": "01.01.2022.03(E)(3)(i)", "rp": "01|01|2022|.03|E.|3.|i.", "x": "Its activities, including any support provided to information privacy or da"}, {"t": "ii.", "p": "/us/md/exec/comar/01.01.2022.03#E3ii", "et": "para", "sc": "01.01.2022.03(E)(3)(ii)", "rp": "01|01|2022|.03|E.|3.|ii.", "x": "Progress on achieving the MD THINK Committee\u2019s objectives and priorities;"}, {"t": "iii.", "p": "/us/md/exec/comar/01.01.2022.03#E3iii", "et": "para", "sc": "01.01.2022.03(E)(3)(iii)", "rp": "01|01|2022|.03|E.|3.|iii.", "x": "The implementation, maintenance, and operation of the Platform;"}, {"t": "iv.", "p": "/us/md/exec/comar/01.01.2022.03#E3iv", "et": "para", "sc": "01.01.2022.03(E)(3)(iv)", "rp": "01|01|2022|.03|E.|3.|iv.", "x": "The products, applications, data, and services in the Portfolio, including "}, {"t": "v.", "p": "/us/md/exec/comar/01.01.2022.03#E3v", "et": "para", "sc": "01.01.2022.03(E)(3)(v)", "rp": "01|01|2022|.03|E.|3.|v.", "x": "Any products, applications, data, or services that are no longer needed onc"}, {"t": "vi.", "p": "/us/md/exec/comar/01.01.2022.03#E3vi", "et": "para", "sc": "01.01.2022.03(E)(3)(vi)", "rp": "01|01|2022|.03|E.|3.|vi.", "x": "All agreements with Participating Units, including the expiration of those "}, {"t": "vii.", "p": "/us/md/exec/comar/01.01.2022.03#E3vii", "et": "para", "sc": "01.01.2022.03(E)(3)(vii)", "rp": "01|01|2022|.03|E.|3.|vii.", "x": "Proposals for any new or additional Participating Units; and"}, {"t": "viii.", "p": "/us/md/exec/comar/01.01.2022.03#E3viii", "et": "para", "sc": "01.01.2022.03(E)(3)(viii)", "rp": "01|01|2022|.03|E.|3.|viii.", "x": "Recommendations for objectives and priorities."}], "x": "Report to the MD THINK Committee about:"}], "x": "The Strategic Initiatives Office shall:"}, {"t": "F.", "p": "/us/md/exec/comar/01.01.2022.03#F", "et": "para", "sc": "01.01.2022.03(F)", "rp": "01|01|2022|.03|F.", "x": "The MD THINK Committee, Executive Director, Operator, and Strategic Initiat"}, {"t": "G.", "p": "/us/md/exec/comar/01.01.2022.03#G", "et": "para", "sc": "01.01.2022.03(G)", "rp": "01|01|2022|.03|G.", "x": "Data on the Platform shall be shared for authorized business and technical "}]}, {"t": "Executive Order 01.01.2022.04", "p": "/us/md/exec/comar/01.01.2022.04", "et": "section", "sc": "01.01.2022.04", "rp": "01|01|2022|.04", "sp": "library|Code of Maryland Regulations|01|01|2022|.04", "c": [{"t": "A.", "p": "/us/md/exec/comar/01.01.2022.04#A", "et": "para", "sc": "01.01.2022.04(A)", "rp": "01|01|2022|.04|A.", "x": "There is a Maryland Behavioral Health and Public Safety Center of Excellenc"}, {"t": "B.", "p": "/us/md/exec/comar/01.01.2022.04#B", "et": "para", "sc": "01.01.2022.04(B)", "rp": "01|01|2022|.04|B.", "c": [{"t": "(1)", "p": "/us/md/exec/comar/01.01.2022.04#B(1)", "et": "para", "sc": "01.01.2022.04(B)(1)", "rp": "01|01|2022|.04|B.|(1)", "c": [{"t": "(a)", "p": "/us/md/exec/comar/01.01.2022.04#B(1)(a)", "et": "para", "sc": "01.01.2022.04(B)(1)(a)", "rp": "01|01|2022|.04|B.|(1)|(a)", "x": "The Lieutenant Governor, or the Lieutenant Governor\u2019s designee;"}, {"t": "(b)", "p": "/us/md/exec/comar/01.01.2022.04#B(1)(b)", "et": "para", "sc": "01.01.2022.04(B)(1)(b)", "rp": "01|01|2022|.04|B.|(1)|(b)", "x": "The Executive Director of the Governor\u2019s Office of Crime Prevention, Youth,"}, {"t": "(c)", "p": "/us/md/exec/comar/01.01.2022.04#B(1)(c)", "et": "para", "sc": "01.01.2022.04(B)(1)(c)", "rp": "01|01|2022|.04|B.|(1)|(c)", "x": "The Secretary of Health, or the Secretary\u2019s designee; and"}, {"t": "(d)", "p": "/us/md/exec/comar/01.01.2022.04#B(1)(d)", "et": "para", "sc": "01.01.2022.04(B)(1)(d)", "rp": "01|01|2022|.04|B.|(1)|(d)", "x": "The Secretary of Public Safety and Correctional Services, or the Secretary\u2019"}, {"t": "(e)", "p": "/us/md/exec/comar/01.01.2022.04#B(1)(e)", "et": "para", "sc": "01.01.2022.04(B)(1)(e)", "rp": "01|01|2022|.04|B.|(1)|(e)", "x": "The Secretary of Disabilities, or the Secretary\u2019s designee."}], "x": "The Group shall consist of the following members:"}, {"t": "(2)", "p": "/us/md/exec/comar/01.01.2022.04#B(2)", "et": "para", "sc": "01.01.2022.04(B)(2)", "rp": "01|01|2022|.04|B.|(2)", "c": [{"t": "(a)", "p": "/us/md/exec/comar/01.01.2022.04#B(2)(a)", "et": "para", "sc": "01.01.2022.04(B)(2)(a)", "rp": "01|01|2022|.04|B.|(2)|(a)", "x": "A designee of the President of the Senate;"}, {"t": "(b)", "p": "/us/md/exec/comar/01.01.2022.04#B(2)(b)", "et": "para", "sc": "01.01.2022.04(B)(2)(b)", "rp": "01|01|2022|.04|B.|(2)|(b)", "x": "A designee of the Speaker of the House of Delegates;"}, {"t": "(c)", "p": "/us/md/exec/comar/01.01.2022.04#B(2)(c)", "et": "para", "sc": "01.01.2022.04(B)(2)(c)", "rp": "01|01|2022|.04|B.|(2)|(c)", "x": "A representative of the Maryland Chiefs of Police Association;"}, {"t": "(d)", "p": "/us/md/exec/comar/01.01.2022.04#B(2)(d)", "et": "para", "sc": "01.01.2022.04(B)(2)(d)", "rp": "01|01|2022|.04|B.|(2)|(d)", "x": "A representative of the Maryland Sheriffs\u2019 Association;"}, {"t": "(e)", "p": "/us/md/exec/comar/01.01.2022.04#B(2)(e)", "et": "para", "sc": "01.01.2022.04(B)(2)(e)", "rp": "01|01|2022|.04|B.|(2)|(e)", "x": "A representative of the Mental Health Association of Maryland;"}, {"t": "(f)", "p": "/us/md/exec/comar/01.01.2022.04#B(2)(f)", "et": "para", "sc": "01.01.2022.04(B)(2)(f)", "rp": "01|01|2022|.04|B.|(2)|(f)", "x": "A representative of the National Alliance on Mental Illness of Maryland; an"}, {"t": "(g)", "p": "/us/md/exec/comar/01.01.2022.04#B(2)(g)", "et": "para", "sc": "01.01.2022.04(B)(2)(g)", "rp": "01|01|2022|.04|B.|(2)|(g)", "x": "A representative of the Substance Abuse and Mental Health Services Administ"}], "x": "The following shall, upon acceptance of membership, be additional Group mem"}, {"t": "(3)", "p": "/us/md/exec/comar/01.01.2022.04#B(3)", "et": "para", "sc": "01.01.2022.04(B)(3)", "rp": "01|01|2022|.04|B.|(3)", "x": "The Governor\u2019s Office of Crime Prevention, Youth, and Victim Services shall"}], "x": "Membership"}, {"t": "C.", "p": "/us/md/exec/comar/01.01.2022.04#C", "et": "para", "sc": "01.01.2022.04(C)", "rp": "01|01|2022|.04|C.", "c": [{"t": "(1)", "p": "/us/md/exec/comar/01.01.2022.04#C(1)", "et": "para", "sc": "01.01.2022.04(C)(1)", "rp": "01|01|2022|.04|C.|(1)", "x": "The Lieutenant Governor or the Lieutenant Governor\u2019s designee shall be Chai"}, {"t": "(2)", "p": "/us/md/exec/comar/01.01.2022.04#C(2)", "et": "para", "sc": "01.01.2022.04(C)(2)", "rp": "01|01|2022|.04|C.|(2)", "c": [{"t": "(a)", "p": "/us/md/exec/comar/01.01.2022.04#C(2)(a)", "et": "para", "sc": "01.01.2022.04(C)(2)(a)", "rp": "01|01|2022|.04|C.|(2)|(a)", "x": "Oversee the work of the Group;"}, {"t": "(b)", "p": "/us/md/exec/comar/01.01.2022.04#C(2)(b)", "et": "para", "sc": "01.01.2022.04(C)(2)(b)", "rp": "01|01|2022|.04|C.|(2)|(b)", "x": "Determine the Group\u2019s agenda; and"}, {"t": "(c)", "p": "/us/md/exec/comar/01.01.2022.04#C(2)(c)", "et": "para", "sc": "01.01.2022.04(C)(2)(c)", "rp": "01|01|2022|.04|C.|(2)|(c)", "x": "Identify additional support needs of the Group."}], "x": "The Chair shall:"}, {"t": "(3)", "p": "/us/md/exec/comar/01.01.2022.04#C(3)", "et": "para", "sc": "01.01.2022.04(C)(3)", "rp": "01|01|2022|.04|C.|(3)", "x": "The Group shall convene as frequently as necessary to satisfy its responsib"}, {"t": "(4)", "p": "/us/md/exec/comar/01.01.2022.04#C(4)", "et": "para", "sc": "01.01.2022.04(C)(4)", "rp": "01|01|2022|.04|C.|(4)", "x": "A majority of the Group\u2019s members is a quorum for the transaction of Group "}, {"t": "(5)", "p": "/us/md/exec/comar/01.01.2022.04#C(5)", "et": "para", "sc": "01.01.2022.04(C)(5)", "rp": "01|01|2022|.04|C.|(5)", "x": "The Group may adopt other procedures as necessary to ensure the orderly tra"}], "x": "Procedures"}, {"t": "D.", "p": "/us/md/exec/comar/01.01.2022.04#D", "et": "para", "sc": "01.01.2022.04(D)", "rp": "01|01|2022|.04|D.", "c": [{"t": "(1)", "p": "/us/md/exec/comar/01.01.2022.04#D(1)", "et": "para", "sc": "01.01.2022.04(D)(1)", "rp": "01|01|2022|.04|D.|(1)", "x": "Advise on the development and implementation of the Maryland Behavioral Hea"}, {"t": "(2)", "p": "/us/md/exec/comar/01.01.2022.04#D(2)", "et": "para", "sc": "01.01.2022.04(D)(2)", "rp": "01|01|2022|.04|D.|(2)", "x": "Support the Center of Excellence\u2019s Sequential Intercept Model as a planning"}, {"t": "(3)", "p": "/us/md/exec/comar/01.01.2022.04#D(3)", "et": "para", "sc": "01.01.2022.04(D)(3)", "rp": "01|01|2022|.04|D.|(3)", "x": "Locate potential federal funding streams that the Center of Excellence can "}, {"t": "(4)", "p": "/us/md/exec/comar/01.01.2022.04#D(4)", "et": "para", "sc": "01.01.2022.04(D)(4)", "rp": "01|01|2022|.04|D.|(4)", "x": "Assist in the creation of repositories of best practices throughout the sta"}, {"t": "(5)", "p": "/us/md/exec/comar/01.01.2022.04#D(5)", "et": "para", "sc": "01.01.2022.04(D)(5)", "rp": "01|01|2022|.04|D.|(5)", "x": "Perform other appropriate duties or responsibilities as recommended by the "}], "x": "The Group shall:"}]}, {"t": "Executive Order 01.01.2022.06", "p": "/us/md/exec/comar/01.01.2022.06", "et": "section", "sc": "01.01.2022.06", "rp": "01|01|2022|.06", "sp": "library|Code of Maryland Regulations|01|01|2022|.06", "c": [{"t": "A.", "p": "/us/md/exec/comar/01.01.2022.06#A", "et": "para", "sc": "01.01.2022.06(A)", "rp": "01|01|2022|.06|A.", "c": [{"t": "(1)", "p": "/us/md/exec/comar/01.01.2022.06#A(1)", "et": "para", "sc": "01.01.2022.06(A)(1)", "rp": "01|01|2022|.06|A.|(1)", "x": "There is a Juvenile Grant Planning and Review Council (the \u201cCouncil\u201d), whic"}, {"t": "(2)", "p": "/us/md/exec/comar/01.01.2022.06#A(2)", "et": "para", "sc": "01.01.2022.06(A)(2)", "rp": "01|01|2022|.06|A.|(2)", "x": "The Council shall be within the Governor's Office of Crime Prevention, Yout"}], "x": "Established."}, {"t": "B.", "p": "/us/md/exec/comar/01.01.2022.06#B", "et": "para", "sc": "01.01.2022.06(B)", "rp": "01|01|2022|.06|B.", "c": [{"t": "(1)", "p": "/us/md/exec/comar/01.01.2022.06#B(1)", "et": "para", "sc": "01.01.2022.06(B)(1)", "rp": "01|01|2022|.06|B.|(1)", "c": [{"t": "(a)", "p": "/us/md/exec/comar/01.01.2022.06#B(1)(a)", "et": "para", "sc": "01.01.2022.06(B)(1)(a)", "rp": "01|01|2022|.06|B.|(1)|(a)", "x": "The Council shall consist of not less than 15 members and not more than 33 "}, {"t": "(b)", "p": "/us/md/exec/comar/01.01.2022.06#B(1)(b)", "et": "para", "sc": "01.01.2022.06(B)(1)(b)", "rp": "01|01|2022|.06|B.|(1)|(b)", "x": "At least one-fifth of the members must be under the age of 28 at the time o"}, {"t": "(c)", "p": "/us/md/exec/comar/01.01.2022.06#B(1)(c)", "et": "para", "sc": "01.01.2022.06(B)(1)(c)", "rp": "01|01|2022|.06|B.|(1)|(c)", "x": "At least 3 members must have been or currently be under the jurisdiction of"}], "x": "Membership."}, {"t": "(2)", "p": "/us/md/exec/comar/01.01.2022.06#B(2)", "et": "para", "sc": "01.01.2022.06(B)(2)", "rp": "01|01|2022|.06|B.|(2)", "x": "The Executive Director of the Governor's Office of Crime Prevention, Youth,"}, {"t": "(3)", "p": "/us/md/exec/comar/01.01.2022.06#B(3)", "et": "para", "sc": "01.01.2022.06(B)(3)", "rp": "01|01|2022|.06|B.|(3)", "c": [{"t": "(a)", "p": "/us/md/exec/comar/01.01.2022.06#B(3)(a)", "et": "para", "sc": "01.01.2022.06(B)(3)(a)", "rp": "01|01|2022|.06|B.|(3)|(a)", "x": "Members may serve up to two consecutive three-year terms, which shall be st"}, {"t": "(b)", "p": "/us/md/exec/comar/01.01.2022.06#B(3)(b)", "et": "para", "sc": "01.01.2022.06(B)(3)(b)", "rp": "01|01|2022|.06|B.|(3)|(b)", "x": "A member selected to fill a vacancy serves only for the balance of a term r"}, {"t": "(c)", "p": "/us/md/exec/comar/01.01.2022.06#B(3)(c)", "et": "para", "sc": "01.01.2022.06(B)(3)(c)", "rp": "01|01|2022|.06|B.|(3)|(c)", "x": "Terms end on June 30 of each year."}, {"t": "(d)", "p": "/us/md/exec/comar/01.01.2022.06#B(3)(d)", "et": "para", "sc": "01.01.2022.06(B)(3)(d)", "rp": "01|01|2022|.06|B.|(3)|(d)", "x": "At the end of a term, a member continues to serve until a successor is appo"}], "x": "Terms."}, {"t": "(4)", "p": "/us/md/exec/comar/01.01.2022.06#B(4)", "et": "para", "sc": "01.01.2022.06(B)(4)", "rp": "01|01|2022|.06|B.|(4)", "x": "Unless otherwise provided by law, the members of the Council shall serve at"}, {"t": "(5)", "p": "/us/md/exec/comar/01.01.2022.06#B(5)", "et": "para", "sc": "01.01.2022.06(B)(5)", "rp": "01|01|2022|.06|B.|(5)", "x": "A majority of the Council shall constitute a quorum for the transaction of "}, {"t": "(6)", "p": "/us/md/exec/comar/01.01.2022.06#B(6)", "et": "para", "sc": "01.01.2022.06(B)(6)", "rp": "01|01|2022|.06|B.|(6)", "x": "The Council may adopt such other procedures, including the creation of subc"}, {"t": "(7)", "p": "/us/md/exec/comar/01.01.2022.06#B(7)", "et": "para", "sc": "01.01.2022.06(B)(7)", "rp": "01|01|2022|.06|B.|(7)", "x": "Members appointed pursuant to \u00a7B(1)(b) and \u00a7B(1)(c) may receive stipends an"}, {"t": "(8)", "p": "/us/md/exec/comar/01.01.2022.06#B(8)", "et": "para", "sc": "01.01.2022.06(B)(8)", "rp": "01|01|2022|.06|B.|(8)", "x": "Members of the Council not appointed pursuant to \u00a7B(1)(b) or \u00a7B(1)(c) may n"}], "x": "Procedures."}, {"t": "C.", "p": "/us/md/exec/comar/01.01.2022.06#C", "et": "para", "sc": "01.01.2022.06(C)", "rp": "01|01|2022|.06|C.", "c": [{"t": "(1)", "p": "/us/md/exec/comar/01.01.2022.06#C(1)", "et": "para", "sc": "01.01.2022.06(C)(1)", "rp": "01|01|2022|.06|C.|(1)", "x": "The Governor's Office of Crime Prevention, Youth, and Victim Services shall"}, {"t": "(2)", "p": "/us/md/exec/comar/01.01.2022.06#C(2)", "et": "para", "sc": "01.01.2022.06(C)(2)", "rp": "01|01|2022|.06|C.|(2)", "x": "A Compliance Monitor shall ensure compliance with federal standards regardi"}, {"t": "(3)", "p": "/us/md/exec/comar/01.01.2022.06#C(3)", "et": "para", "sc": "01.01.2022.06(C)(3)", "rp": "01|01|2022|.06|C.|(3)", "c": [{"t": "(a)", "p": "/us/md/exec/comar/01.01.2022.06#C(3)(a)", "et": "para", "sc": "01.01.2022.06(C)(3)(a)", "rp": "01|01|2022|.06|C.|(3)|(a)", "x": "Primarily focus on addressing R/ED within the State's Juvenile Justice Syst"}, {"t": "(b)", "p": "/us/md/exec/comar/01.01.2022.06#C(3)(b)", "et": "para", "sc": "01.01.2022.06(C)(3)(b)", "rp": "01|01|2022|.06|C.|(3)|(b)", "x": "Provide technical assistance as necessary and appropriate."}], "x": "A Racial and Ethnic Disparities (\u201cR/ED\u201d) Coordinator shall:"}], "x": "Staffing."}, {"t": "D.", "p": "/us/md/exec/comar/01.01.2022.06#D", "et": "para", "sc": "01.01.2022.06(D)", "rp": "01|01|2022|.06|D.", "c": [{"t": "(1)", "p": "/us/md/exec/comar/01.01.2022.06#D(1)", "et": "para", "sc": "01.01.2022.06(D)(1)", "rp": "01|01|2022|.06|D.|(1)", "x": "The Council shall perform the functions, and have the duties and responsibi"}, {"t": "(2)", "p": "/us/md/exec/comar/01.01.2022.06#D(2)", "et": "para", "sc": "01.01.2022.06(D)(2)", "rp": "01|01|2022|.06|D.|(2)", "x": "The Council shall be afforded the opportunity to review all Title II Formul"}, {"t": "(3)", "p": "/us/md/exec/comar/01.01.2022.06#D(3)", "et": "para", "sc": "01.01.2022.06(D)(3)", "rp": "01|01|2022|.06|D.|(3)", "x": "The Council shall provide advice to the Governor's Office of Crime Preventi"}, {"t": "(4)", "p": "/us/md/exec/comar/01.01.2022.06#D(4)", "et": "para", "sc": "01.01.2022.06(D)(4)", "rp": "01|01|2022|.06|D.|(4)", "x": "The Council shall advise the Compliance Monitor, R/ED Coordinator, and Juve"}, {"t": "(5)", "p": "/us/md/exec/comar/01.01.2022.06#D(5)", "et": "para", "sc": "01.01.2022.06(D)(5)", "rp": "01|01|2022|.06|D.|(5)", "x": "The Compliance Monitor, R/ED Coordinator, and Juvenile Justice Specialist s"}, {"t": "(6)", "p": "/us/md/exec/comar/01.01.2022.06#D(6)", "et": "para", "sc": "01.01.2022.06(D)(6)", "rp": "01|01|2022|.06|D.|(6)", "x": "The Council shall perform any additional duties as directed by the Executiv"}], "x": "Duties and Responsibilities."}, {"t": "E.", "p": "/us/md/exec/comar/01.01.2022.06#E", "et": "para", "sc": "01.01.2022.06(E)", "rp": "01|01|2022|.06|E.", "x": "On or before June 30 of each year, the Council shall report to the Governor"}, {"t": "F.", "p": "/us/md/exec/comar/01.01.2022.06#F", "et": "para", "sc": "01.01.2022.06(F)", "rp": "01|01|2022|.06|F.", "c": [{"t": "(1)", "p": "/us/md/exec/comar/01.01.2022.06#F(1)", "et": "para", "sc": "01.01.2022.06(F)(1)", "rp": "01|01|2022|.06|F.|(1)", "x": "The Council shall acknowledge and abide by policies and procedures set fort"}, {"t": "(2)", "p": "/us/md/exec/comar/01.01.2022.06#F(2)", "et": "para", "sc": "01.01.2022.06(F)(2)", "rp": "01|01|2022|.06|F.|(2)", "x": "The procedures shall provide that Council members may not participate in an"}], "x": "Conflicts of Interest"}]}]}