{"t": "Chapter 57 International Green Construction Code", "p": "/us/md/exec/comar/09.12.57", "et": "container", "dj": "/us/md/exec/comar/index.json", "fh": "/us/md/exec/comar/09.12.57/index.full.html", "sc": "09.12.57", "rp": "09|12|57", "sp": "library|Code of Maryland Regulations|09|12|57", "c": [{"t": ".01 Purpose.", "p": "/us/md/exec/comar/09.12.57.01", "et": "section", "sc": "09.12.57.01", "rp": "09|12|57|.01", "sp": "library|Code of Maryland Regulations|09|12|57|.01"}, {"t": ".02 Incorporation by Reference.", "p": "/us/md/exec/comar/09.12.57.02", "et": "section", "sc": "09.12.57.02", "rp": "09|12|57|.02", "sp": "library|Code of Maryland Regulations|09|12|57|.02"}]}